resurfemg/__init__.py
resurfemg/__main__.py
resurfemg/__version__.py
resurfemg/cli/__init__.py
resurfemg/cli/cli.py
resurfemg/data_connector/__init__.py
resurfemg/data_connector/adicht_reader.py
resurfemg/data_connector/config.py
resurfemg/data_connector/converter_functions.py
resurfemg/data_connector/data_classes.py
resurfemg/data_connector/file_discovery.py
resurfemg/data_connector/peakset_class.py
resurfemg/data_connector/synthetic_data.py
resurfemg/data_connector/tmsisdk_lite.py
resurfemg/helper_functions/__init__.py
resurfemg/helper_functions/data_classes_quality_assessment.py
resurfemg/helper_functions/math_operations.py
resurfemg/helper_functions/visualization.py
resurfemg/pipelines/__init__.py
resurfemg/pipelines/ipy_widgets.py
resurfemg/pipelines/processing.py
resurfemg/pipelines/synthetic_data.py
resurfemg/postprocessing/__init__.py
resurfemg/postprocessing/baseline.py
resurfemg/postprocessing/event_detection.py
resurfemg/postprocessing/features.py
resurfemg/postprocessing/quality_assessment.py
resurfemg/preprocessing/__init__.py
resurfemg/preprocessing/ecg_removal.py
resurfemg/preprocessing/envelope.py
resurfemg/preprocessing/filtering.py
resurfemg-1.1.0.dist-info/licenses/LICENSE
resurfemg-1.1.0.dist-info/METADATA
resurfemg-1.1.0.dist-info/WHEEL
resurfemg-1.1.0.dist-info/top_level.txt
resurfemg-1.1.0.dist-info/RECORD
