Metadata-Version: 2.4
Name: resurfemg
Version: 1.1.0
Summary: A package for analysis of respiratory EMG data
Maintainer-email: Eline Mos-Oppersma <e.oppersma@utwente.nl>, Rob Warnaar <r.s.p.warnaar@utwente.nl>
License: Apache-2.0
Project-URL: Homepage, https://github.com/ReSurfEMG-org
Project-URL: Documentation, https://resurfemg-org.github.io/ReSurfEMG/
Project-URL: Repository, https://github.com/resurfemg-org/ReSurfEMG
Project-URL: Issues, https://github.com/resurfemg-org/ReSurfEMG/issues
Project-URL: Changelog, https://github.com/resurfemg-org/ReSurfEMG/blob/main/CHANGELOG.md
Keywords: electromyography,EMG,respiratory,Python,surface EMG
Classifier: Programming Language :: Python :: 3.9
Classifier: Programming Language :: Python :: 3.10
Classifier: Programming Language :: Python :: 3.11
Classifier: Programming Language :: Python :: 3.12
Classifier: License :: OSI Approved :: Apache Software License
Classifier: Operating System :: OS Independent
Requires-Python: >=3.9
License-File: LICENSE
Requires-Dist: pyxdf
Requires-Dist: mne>=0.23.4
Requires-Dist: textdistance
Requires-Dist: pandas
Requires-Dist: scipy
Requires-Dist: matplotlib
Requires-Dist: h5py
Requires-Dist: numpy>=1.24.4
Requires-Dist: scikit-learn>=1.3.2
Requires-Dist: neurokit2>=0.2.7
Requires-Dist: pywavelets>=1.1.1
Requires-Dist: adi-reader>=0.0.13
Requires-Dist: prettytable>=3.12.0
Provides-Extra: tests
Requires-Dist: pytest; extra == "tests"
Requires-Dist: pytest-cov; extra == "tests"
Requires-Dist: pycodestyle; extra == "tests"
Requires-Dist: isort; extra == "tests"
Requires-Dist: wheel; extra == "tests"
Requires-Dist: ipywidgets; extra == "tests"
Provides-Extra: docs
Requires-Dist: wheel; extra == "docs"
Requires-Dist: sphinx; extra == "docs"
Requires-Dist: ipywidgets; extra == "docs"
Provides-Extra: dev
Requires-Dist: pytest; extra == "dev"
Requires-Dist: pytest-cov; extra == "dev"
Requires-Dist: pycodestyle; extra == "dev"
Requires-Dist: isort; extra == "dev"
Requires-Dist: wheel; extra == "dev"
Requires-Dist: jupyter; extra == "dev"
Requires-Dist: ipympl; extra == "dev"
Requires-Dist: sphinx; extra == "dev"
Requires-Dist: twine; extra == "dev"
Dynamic: license-file
